pipecraft/__init__.py
pipecraft/node.py
pipecraft/pipeline.py
pipecraft/utils.py
pipecraft/backend/__init__.py
pipecraft/backend/aws_batch.py
pipecraft/backend/base.py
pipecraft/backend/snakemake.py
pipecraft/backend/templates/__init__.py
pipecraft/backend/templates/nexflow.config.mako
pipecraft/backend/templates/snakemake.mako
pipecraft/backend/templates/workflow.nf.mako
pipecraft-0.16.0.dist-info/METADATA
pipecraft-0.16.0.dist-info/WHEEL
pipecraft-0.16.0.dist-info/top_level.txt
pipecraft-0.16.0.dist-info/RECORD
