Metadata-Version: 2.1
Name: pipecraft
Version: 0.16.0
Summary: Library and tools to build and execute pipelines
Author-email: Ankur Kumar <ank@leoank.me>
Requires-Python: >=3.10
Requires-Dist: pydantic<3.0,>=2.6
Requires-Dist: networkx<4.0,>=3.2
Requires-Dist: matplotlib<4.0,>=3.8
Requires-Dist: Mako<2.0,>=1.3.5
Requires-Dist: cloudpathlib[all]<1.0,>=0.18
Provides-Extra: dev
Requires-Dist: pytest>=8.2; extra == "dev"
Requires-Dist: ruff>=0.5; extra == "dev"
Requires-Dist: build>=1.2; extra == "dev"
Requires-Dist: twine>=5.1; extra == "dev"
